{
  "species": "cobblemon:ironflare",
  "order": 1,
  "variations": [
    {
      "aspects": ["mega"],
      "poser": "cobblemon:ironflare_mega",
      "model": "cobblemon:ironflare_mega.geo",
      "texture": "cobblemon:textures/pokemon/ironflare/ironflare_mega.png",
      "layers": [
        {
          "name": "emissive",
          "texture": "cobblemon:textures/pokemon/ironflare/ironflare_mega_emissive.png",
          "emissive": "true"
        }
      ]
    },
    {
      "aspects": ["mega", "sleep"],
      "texture": "cobblemon:textures/pokemon/ironflare/ironflare_mega_sleep.png"
    },
    {
      "aspects": ["mega", "shiny"],
      "texture": "cobblemon:textures/pokemon/ironflare/ironflare_mega_shiny.png",
      "layers": [
        {
          "name": "emissive",
          "texture": "cobblemon:textures/pokemon/ironflare/ironflare_mega_shiny_emissive.png",
          "emissive": "true"
        }
      ]
    }
  ]
}
