{
  "CONFIG_VERSION": 4,
  "effectSettings": {
    "shinyBoostMultiplier": 4.0,
    "superShinyBoostMultiplier": 8.0,
    "ultraShinyBoostMultiplier": 12.0,
    "uncommonBoostMultiplier": 16.0,
    "rareBoostMultiplier": 16.0,
    "ultraRareBoostMultiplier": 16.0,
    "ultraBeastBoostMultiplier": 10.0,
    "paradoxBoostMultiplier": 10.0,
    "legendaryBoostMultiplier": 10.0,
    "mythicalBoostMultiplier": 10.0,
    "effectDistanceBlocks": 80.0,
    "alphaPowerLevel1BoostMultiplier": 11.0,
    "alphaPowerLevel2BoostMultiplier": 21.0,
    "alphaPowerLevel3BoostMultiplier": 51.0,
    "hiddenPowerLevel1BoostMultiplier": 2.0,
    "hiddenPowerLevel2BoostMultiplier": 3.0,
    "hiddenPowerLevel3BoostMultiplier": 4.0,
    "friendshipPowerLevel1Bonus": 50,
    "friendshipPowerLevel2Bonus": 75,
    "friendshipPowerLevel3Bonus": 100,
    "capturePowerLevel1Multiplier": 1.1,
    "capturePowerLevel2Multiplier": 1.2,
    "capturePowerLevel3Multiplier": 1.3,
    "encounterPowerLevel1SpawnBonus": 0.1,
    "encounterPowerLevel2SpawnBonus": 0.25,
    "encounterPowerLevel3SpawnBonus": 0.5,
    "humongoPowerLevel1LevelDelta": 5,
    "humongoPowerLevel2LevelDelta": 10,
    "humongoPowerLevel3LevelDelta": 15,
    "teensyPowerLevel1LevelLoss": 5,
    "teensyPowerLevel2LevelLoss": 10,
    "teensyPowerLevel3LevelLoss": 15,
    "luckPowerLevel1LuckBonus": 1.0,
    "luckPowerLevel2LuckBonus": 3.0,
    "luckPowerLevel3LuckBonus": 5.0,
    "salvagePowerLevel1ExtraRolls": 1,
    "salvagePowerLevel2ExtraRolls": 2,
    "salvagePowerLevel3ExtraRolls": 3,
    "partyBattleStatPowerLevel1Multiplier": 1.1,
    "partyBattleStatPowerLevel2Multiplier": 1.25,
    "partyBattleStatPowerLevel3Multiplier": 1.5,
    "moveResistanceEvBudgetFactor": 0.8,
    "selfAttackPowerLevel1DamageMultiplier": 1.1,
    "selfAttackPowerLevel2DamageMultiplier": 1.25,
    "selfAttackPowerLevel3DamageMultiplier": 1.5,
    "selfDefensePowerLevel1DamageTakenMultiplier": 0.9,
    "selfDefensePowerLevel2DamageTakenMultiplier": 0.75,
    "selfDefensePowerLevel3DamageTakenMultiplier": 0.5
  },
  "durationSettings": {
    "shinyBoostDuration": 6000,
    "superShinyBoostDuration": 6000,
    "ultraShinyBoostDuration": 6000,
    "uncommonBoostDuration": 6000,
    "rareBoostDuration": 6000,
    "ultraRareBoostDuration": 6000,
    "repelDuration": 6000,
    "ultraBeastBoostDuration": 6000,
    "paradoxBoostDuration": 6000,
    "legendaryBoostDuration": 6000,
    "mythicalBoostDuration": 6000
  }
}