{
    "enabled": true,
    "neededInstalledMods": [],
    "neededUninstalledMods": [],
    "spawns": [
	{
            "id": "bronzor_ride2",
            "pokemon": "bronzor",
            "presets": [
                "natural"
            ],
           "type": "pokemon",
           "context": "grounded",
            "bucket": "common",
            "level": "13-32",
            "weight": 1000.00,
            "condition": {
		"maxX": -601,
		"minX": -625,
		"maxZ": 139,
		"minZ": 110,
        "maxY": 124,
        "minY": 74
            }
        }
    ]
}