{
    "enabled": true,
    "neededInstalledMods": [],
    "neededUninstalledMods": [],
    "spawns": [
	{
            "id": "metagross_ride",
            "pokemon": "metagross",
            "presets": [
                "natural"
            ],
           "type": "pokemon",
            "context": "grounded",
            "bucket": "rare",
            "level": "51-62",
            "weight": 800.00,
            "condition": {
		"canSeeSky": true,
		"maxX": -612,
		"minX": -859,
		"maxZ": -17,
		"minZ": -558,
        "maxY": 182,
        "minY": 60,
        "biomes": [
                    "#cobblemon:is_frozen_ocean"
        ],
        "neededNearbyBlocks": [
                    "minecraft:stone",
                    "minecraft:grass_block",
                    "minecraft:coarse_dirt"
                ]
            }
        }
    ]
}