{
    "enabled": true,
    "neededInstalledMods": [],
    "neededUninstalledMods": [],
    "spawns": [
	{
            "id": "lumineon_fish",
           "pokemon": "lumineon",
            "presets": [
                "underwater"
            ],
            "type": "pokemon",
            "context": "submerged",
            "bucket": "uncommon",
            "level": "32-44",
            "weight": 800.00,
            "condition": {
		"maxX": -275,
		"minX": -544,
		"maxZ": 860,
		"minZ": 540,
                "biomes": [
                    "#cobblemon:is_overworld"
		]
            }
        }
    ]
}