{
    "enabled": true,
    "neededInstalledMods": [],
    "neededUninstalledMods": [],
    "spawns": [
	{
            "id": "wimpod_fish2",
            "pokemon": "wimpod",
           "presets": [
                "underwater"
            ],
            "type": "pokemon",
            "context": "seafloor",
            "bucket": "common",
            "level": "4-28",
            "weight": 1000.00,
            "condition": {
		"maxX": -302,
		"minX": -349,
		"maxZ": 750,
		"minZ": 721,
                "biomes": [
                    "#cobblemon:is_overworld"
		]
            }
        }
    ]
}