{
  "enabled": true,
  "neededInstalledMods": [],
  "neededUninstalledMods": [],
  "spawns": [
    {
      "id": "deeper-greattusk-1",
      "pokemon": "greattusk",
      "presets": [
        "deep_dark"
      ],
      "type": "pokemon",
      "spawnablePositionType": "grounded",
      "bucket": "rare",
      "level": "47-67",
      "weight": 2.12,
      "condition": {
        "biomes": [
          "deeperdarker:overcast_columns"
        ],
        "dimensions": [
          "deeperdarker:otherside"
        ]
      }
    },
    {
      "id": "aether_great_tusk_1",
      "pokemon": "greattusk",
      "presets": [
        "natural"
      ],
      "type": "pokemon",
      "context": "grounded",
      "bucket": "rare",
      "level": "50-100",
      "weight": 5.0,
      "condition": {
        "biomes": [
          "aether:skyroot_meadow"
        ],
        "dimensions": [
          "aether:the_aether"
        ]
      }
    }
  ]
}
